manager_hj3415/__init__.py
manager_hj3415/manager.py
manager_hj3415-0.1.2.data/scripts/manager.py
manager_hj3415-0.1.2.dist-info/LICENSE
manager_hj3415-0.1.2.dist-info/METADATA
manager_hj3415-0.1.2.dist-info/WHEEL
manager_hj3415-0.1.2.dist-info/top_level.txt
manager_hj3415-0.1.2.dist-info/RECORD
